[
  {
    "dataset": "FEMTO",
    "window_size": 2560,
    "seed": 42,
    "epochs": 30,
    "n_minority_samples": 870,
    "input_dim": 5,
    "target_min": 0.0011481055989861488,
    "target_max": 0.19977037608623505,
    "target_mean": 0.10045924220212746,
    "num_params": 856482,
    "train_time_s": 17.18,
    "gen_time_s": 2.3,
    "status": "success",
    "real_mean": 0.198877,
    "synth_mean": 0.197081,
    "real_std": 1.524246,
    "synth_std": 0.603187,
    "mean_abs_diff": 0.001796,
    "std_abs_diff": 0.921059,
    "power_spectrum_l2": 11811.437795,
    "power_spectrum_corr": 0.961716,
    "mmd": 0.238228
  },
  {
    "dataset": "XJTU-SY",
    "window_size": 2048,
    "seed": 42,
    "epochs": 30,
    "n_minority_samples": 390,
    "input_dim": 2,
    "target_min": 0.0030674845911562443,
    "target_max": 0.19938650727272034,
    "target_mean": 0.10122699368601808,
    "num_params": 831810,
    "train_time_s": 14.2,
    "gen_time_s": 2.08,
    "status": "success",
    "real_mean": 0.000731,
    "synth_mean": 0.039207,
    "real_std": 1.666496,
    "synth_std": 1.338031,
    "mean_abs_diff": 0.038476,
    "std_abs_diff": 0.328465,
    "power_spectrum_l2": 26390.287234,
    "power_spectrum_corr": 0.298552,
    "mmd": 0.049186
  }
]